MetricsUtils/__init__.py
MetricsUtils/blobStorage.py
MetricsUtils/hpStatisticsCollection.py
MetricsUtils/keyVault.py
MetricsUtils/storageutils.py
azure_utils/__init__.py
azure_utils/utilities.py
azure_utils/configuration/__init__.py
azure_utils/configuration/configuration_ui.py
azure_utils/configuration/configuration_validation.py
azure_utils/configuration/notebook_config.py
azure_utils/configuration/project_configuration.py
azure_utils/dev_ops/__init__.py
azure_utils/dev_ops/testing_utilities.py
azure_utils/machine_learning/__init__.py
azure_utils/machine_learning/create_model.py
azure_utils/machine_learning/duplicate_model.py
azure_utils/machine_learning/item_selector.py
azure_utils/machine_learning/label_rank.py
azure_utils/machine_learning/register_datastores.py
azure_utils/machine_learning/utils.py
azure_utils/machine_learning/realtime/__init__.py
azure_utils/machine_learning/realtime/image.py
azure_utils/machine_learning/realtime/kubernetes.py
azureml_tools/__init__.py
azureml_tools/config.py
azureml_tools/experiment.py
azureml_tools/resource_group.py
azureml_tools/storage.py
azureml_tools/subscription.py
azureml_tools/workspace.py
notebooks/__init__.py
tests/__init__.py
tests/test_notebooks.py
tests/utils.py
tests/configuration/__init__.py
tests/configuration/test_config.py
tests/configuration/test_validation.py
tests/machine_learning/__init__.py
tests/machine_learning/test_realtime.py
tests/machine_learning/test_register_datastores.py
tests/machine_learning/test_utils.py
Microsoft_AI_Azure_Utility_Samples-0.3.7.dist-info/LICENSE
Microsoft_AI_Azure_Utility_Samples-0.3.7.dist-info/METADATA
Microsoft_AI_Azure_Utility_Samples-0.3.7.dist-info/WHEEL
Microsoft_AI_Azure_Utility_Samples-0.3.7.dist-info/top_level.txt
Microsoft_AI_Azure_Utility_Samples-0.3.7.dist-info/RECORD
