Metadata-Version: 2.1
Name: Microsoft-AI-Azure-Utility-Samples
Version: 0.3.7
Summary: Utility Samples for AI Solutions
Home-page: https://github.com/microsoft/AI-Utilities
Author: Daniel Ciborowski & Daniel Grecoe
Author-email: dciborow@microsoft.com
License: MIT
Platform: UNKNOWN
Requires-Dist: azureml-core
Requires-Dist: azure-cli (==2.0.81)
Requires-Dist: python-dotenv
Requires-Dist: nbformat
Requires-Dist: papermill
Requires-Dist: nbconvert
Requires-Dist: junit-xml
Requires-Dist: PyYAML
Requires-Dist: pytest
Requires-Dist: lightgbm (==2.1.2)
Requires-Dist: pandas
Requires-Dist: sklearn
Requires-Dist: msrestazure
Requires-Dist: azure-common
Requires-Dist: azure-cli-ml
Requires-Dist: deprecated
